draftdiff/aggregation.py
draftdiff/aggregation2.py
draftdiff/constants.py
draftdiff/dotabuff.py
draftdiff/io.py
draftdiff/main.py
draftdiff/main2.py
draftdiff/sheets.py
draftdiff/stratz.py
draftdiff/util.py
draftdiff/writetos3.py
draftdiff/writetosheets.py
draftdiff-0.1.8.dist-info/LICENSE
draftdiff-0.1.8.dist-info/METADATA
draftdiff-0.1.8.dist-info/WHEEL
draftdiff-0.1.8.dist-info/RECORD
