Metadata-Version: 2.1
Name: draftdiff
Version: 0.1.8
Summary: creating dota2 counterpicker
License: MIT
Author: Jeff
Requires-Python: ==3.11.0
Classifier: License :: OSI Approved :: MIT License
Classifier: Programming Language :: Python :: 3
Classifier: Programming Language :: Python :: 3.11
Requires-Dist: awscli (>=1.33.4,<2.0.0)
Requires-Dist: beautifulsoup4 (>=4.12.3,<5.0.0)
Requires-Dist: boto3 (>=1.34.122,<2.0.0)
Requires-Dist: google-api-python-client (>=2.125.0,<3.0.0)
Requires-Dist: google-auth (>=2.29.0,<3.0.0)
Requires-Dist: gspread (>=6.1.0,<7.0.0)
Requires-Dist: loguru (>=0.7.2,<0.8.0)
Requires-Dist: oauth2client (>=4.1.3,<5.0.0)
Requires-Dist: pandas (>=2.2.1,<3.0.0)
Requires-Dist: pyarrow (>=16.1.0,<17.0.0)
Requires-Dist: requests (>=2.31.0,<3.0.0)
Requires-Dist: tqdm (>=4.66.2,<5.0.0)
